bordersandpoints/__init__.py
bordersandpoints/border_lines.py
bordersandpoints-1.1.1.dist-info/METADATA
bordersandpoints-1.1.1.dist-info/WHEEL
bordersandpoints-1.1.1.dist-info/top_level.txt
bordersandpoints-1.1.1.dist-info/RECORD
