Metadata-Version: 2.1
Name: bordersandpoints
Version: 1.1.1
Summary: Library for finding border lines with point in 2D video
Author: Malla Dhanraj
Requires-Dist: numpy
Requires-Dist: opencv-python
Requires-Dist: matplotlib
Requires-Dist: Pillow
Requires-Dist: torch
Requires-Dist: torchvision
Requires-Dist: scikit-learn
